nonebot/adapters/ding/__init__.py
nonebot/adapters/ding/bot.py
nonebot/adapters/ding/config.py
nonebot/adapters/ding/event.py
nonebot/adapters/ding/exception.py
nonebot/adapters/ding/message.py
nonebot/adapters/ding/utils.py
nonebot_adapter_ding-2.0.0a16.dist-info/WHEEL
nonebot_adapter_ding-2.0.0a16.dist-info/METADATA
nonebot_adapter_ding-2.0.0a16.dist-info/RECORD
