Metadata-Version: 2.1
Name: nonebot-adapter-ding
Version: 2.0.0a16
Summary: Ding adapter for nonebot2
Home-page: https://v2.nonebot.dev/
License: MIT
Keywords: bot,qq,qqbot,ding
Author: Artin
Author-email: lengthmin@gmail.com
Requires-Python: >=3.7.3,<4.0.0
Classifier: Development Status :: 5 - Production/Stable
Classifier: Framework :: Robot Framework
Classifier: Framework :: Robot Framework :: Library
Classifier: License :: OSI Approved :: MIT License
Classifier: Operating System :: OS Independent
Classifier: Programming Language :: Python :: 3
Classifier: Programming Language :: Python :: 3.8
Classifier: Programming Language :: Python :: 3.9
Requires-Dist: httpx (>=0.18.0,<1.0.0)
Requires-Dist: nonebot2 (>=2.0.0-alpha.14,<3.0.0)
Project-URL: Documentation, https://v2.nonebot.dev/
Project-URL: Repository, https://github.com/nonebot/nonebot2
